client/__init__.py
client/clnt.py
client/client/__init__.py
client/client/add_contact_dialog.py
client/client/client_database.py
client/client/client_thread.py
client/client/del_contact_dialog.py
client/client/main_win.py
client/client/main_win_converted.py
client/client/start_dialog.py
client/common/__init__.py
client/common/decos.py
client/common/descriptors.py
client/common/errors.py
client/common/metaclasses.py
client/common/utils.py
client/common/variables.py
client/logs/__init__.py
client/logs/config_log_client.py
client/logs/config_log_other.py
client/logs/config_log_server.py
client/unit_tests/__init__.py
client/unit_tests/test_client.py
client/unit_tests/test_server.py
messager_client-0.0.1.dist-info/METADATA
messager_client-0.0.1.dist-info/WHEEL
messager_client-0.0.1.dist-info/top_level.txt
messager_client-0.0.1.dist-info/RECORD
