Metadata-Version: 2.1
Name: messager-client
Version: 0.0.1
Summary: client_for_messeger
Home-page: UNKNOWN
Author: KolesnikIvan
License: UNKNOWN
Platform: UNKNOWN
Requires-Dist: PyQt5
Requires-Dist: sqlalchemy
Requires-Dist: pycryptodome
Requires-Dist: pycryptodomex
